my_santander_finance/__init__.py
my_santander_finance/config/settings.py
my_santander_finance/dashboard.py
my_santander_finance/database/mydatabase.py
my_santander_finance/database/sqlite.sql
my_santander_finance/database/table_amex_add_id_autoincrement.sql
my_santander_finance/database/table_debit_add_id_autoincrement.sql
my_santander_finance/database/table_visa_add_id_autoincrement.sql
my_santander_finance/definitions.py
my_santander_finance/driver/chromedriver.exe
my_santander_finance/driver/chromedriver.url
my_santander_finance/init.py
my_santander_finance/logger/__init__.py
my_santander_finance/logger/logger.py
my_santander_finance/sanfi.py
my_santander_finance/tags/dict.py
my_santander_finance/tags/insert_tag.py
my_santander_finance/util/func_chrome.py
my_santander_finance/util/func_dir.py
my_santander_finance/util/func_excel.py
my_santander_finance/util/func_files.py
my_santander_finance/web_scraping/get_amex.py
my_santander_finance/web_scraping/get_debito.py
my_santander_finance/web_scraping/get_visa.py
my_santander_finance/web_scraping/import_amex.py
my_santander_finance/web_scraping/import_debito.py
my_santander_finance/web_scraping/import_visa.py
my_santander_finance/web_scraping/santander_scraping.py
my_santander_finance-0.3.6.dist-info/entry_points.txt
my_santander_finance-0.3.6.dist-info/LICENSE
my_santander_finance-0.3.6.dist-info/METADATA
my_santander_finance-0.3.6.dist-info/WHEEL
my_santander_finance-0.3.6.dist-info/RECORD
